package_root/__init__.py
package_root-1.0.0.dist-info/WHEEL
package_root-1.0.0.dist-info/METADATA
package_root-1.0.0.dist-info/RECORD
