Metadata-Version: 2.1
Name: package-root
Version: 1.0.0
Summary: import package_root # into your PYTHON_PATH
Home-page: https://github.com/fny/python-package_root
License: MIT
Keywords: package_root,project,root,path,python,utlity,common,root,rootpath,root-path,detect,autodetect,auto-detect,project-root,project-root-path,package-root,package-root-path
Author: Faraz Yashar
Author-email: faraz.yashar@gmail.com
Requires-Python: >=3.7
Classifier: Development Status :: 5 - Production/Stable
Classifier: Intended Audience :: Developers
Classifier: License :: OSI Approved :: MIT License
Classifier: Programming Language :: Python :: 3
Classifier: Programming Language :: Python :: 3.10
Classifier: Programming Language :: Python :: 3.7
Classifier: Programming Language :: Python :: 3.8
Classifier: Programming Language :: Python :: 3.9
Classifier: Topic :: Software Development :: Libraries :: Python Modules
Project-URL: Documentation, https://github.com/fny/python-package_root
Project-URL: Repository, https://github.com/fny/python-package_root
